{
	"format_version": "1.21.11",
	"ambientocclusion": false,
	"textures": {
		"0": "pspp:block/dummy",
		"1": "pspp:block/dummy",
		"2": "pspp:block/dummy",
		"3": "pspp:block/dummy",
		"particle": "pspp:block/dummy"
	},
	"elements": [
		{
			"from": [0, 0, 0],
			"to": [16, 16, 16],
			"faces": {
				"north": {"uv": [0, 0, 16, 16], "texture": "#2"},
				"east": {"uv": [0, 0, 16, 16], "texture": "#1", "cullface": "east"},
				"south": {"uv": [0, 0, 16, 16], "texture": "#1", "cullface": "south"},
				"west": {"uv": [0, 0, 16, 16], "texture": "#2"},
				"up": {"uv": [0, 0, 16, 16], "texture": "#0"},
				"down": {"uv": [0, 16, 16, 0], "texture": "#0"}
			}
		},
		{
			"from": [0.82843, -0.1, 14],
			"to": [23.45584, 16.1, 15],
			"rotation": {"angle": 45, "axis": "y", "origin": [2.82843, 14, 16]},
			"faces": {
				"north": {"uv": [0, 0, 16, 16], "texture": "#1"},
				"up": {"uv": [16, 0, 0, 1], "texture": "#1"},
				"down": {"uv": [16, 15, 0, 16], "texture": "#1"}
			}
		},
		{
			"from": [0.82843, 13, 13.9],
			"to": [23.45584, 16.2, 15.9],
			"shade": false,
			"rotation": {"angle": 45, "axis": "y", "origin": [2.82843, 14, 16]},
			"faces": {
				"north": {"uv": [2, 0, 14, 3], "texture": "#3"},
				"up": {"uv": [14, 1, 2, 3], "texture": "#3"}
			}
		},
		{
			"from": [0.82843, -0.2, 14.05],
			"to": [23.45584, 3, 15.95],
			"rotation": {"angle": 45, "axis": "y", "origin": [2.82843, 2, 16]},
			"faces": {
				"down": {"uv": [14, 3, 2, 1], "texture": "#3"}
			}
		}
	]
}